odoo/addons/stock_secondary_unit/README.rst
odoo/addons/stock_secondary_unit/__init__.py
odoo/addons/stock_secondary_unit/__manifest__.py
odoo/addons/stock_secondary_unit/i18n/es.po
odoo/addons/stock_secondary_unit/i18n/fi.po
odoo/addons/stock_secondary_unit/i18n/hr.po
odoo/addons/stock_secondary_unit/i18n/it.po
odoo/addons/stock_secondary_unit/i18n/stock_secondary_unit.pot
odoo/addons/stock_secondary_unit/i18n/zh_CN.po
odoo/addons/stock_secondary_unit/models/__init__.py
odoo/addons/stock_secondary_unit/models/product_product.py
odoo/addons/stock_secondary_unit/models/product_template.py
odoo/addons/stock_secondary_unit/models/stock_move.py
odoo/addons/stock_secondary_unit/models/stock_product_secondary_unit_mixin.py
odoo/addons/stock_secondary_unit/readme/CONTRIBUTORS.md
odoo/addons/stock_secondary_unit/readme/DESCRIPTION.md
odoo/addons/stock_secondary_unit/readme/USAGE.md
odoo/addons/stock_secondary_unit/report/report_deliveryslip.xml
odoo/addons/stock_secondary_unit/static/description/icon.png
odoo/addons/stock_secondary_unit/static/description/index.html
odoo/addons/stock_secondary_unit/tests/__init__.py
odoo/addons/stock_secondary_unit/tests/test_stock_secondary_unit.py
odoo/addons/stock_secondary_unit/views/product_views.xml
odoo/addons/stock_secondary_unit/views/stock_move_views.xml
odoo/addons/stock_secondary_unit/views/stock_picking_views.xml
odoo_addon_stock_secondary_unit-18.0.1.0.0.4.dist-info/METADATA
odoo_addon_stock_secondary_unit-18.0.1.0.0.4.dist-info/WHEEL
odoo_addon_stock_secondary_unit-18.0.1.0.0.4.dist-info/top_level.txt
odoo_addon_stock_secondary_unit-18.0.1.0.0.4.dist-info/RECORD
