Metadata-Version: 2.1
Name: odoo-addon-stock_secondary_unit
Version: 18.0.1.0.0.4
Requires-Python: >=3.10
Requires-Dist: odoo-addon-product_secondary_unit==18.0.*
Requires-Dist: odoo==18.0.*
Summary: Get product quantities in a secondary unit
Home-page: https://github.com/OCA/stock-logistics-warehouse
License: AGPL-3
Author: Tecnativa, Odoo Community Association (OCA)
Author-email: support@odoo-community.org
Classifier: Programming Language :: Python
Classifier: Framework :: Odoo
Classifier: Framework :: Odoo :: 18.0
Classifier: License :: OSI Approved :: GNU Affero General Public License v3
Classifier: Development Status :: 5 - Production/Stable
